{
  "dataset": "support_groups_full_164_loo",
  "model": "neumf_baseline",
  "seed": 62,
  "entity": "item",
  "repr": "main",
  "preprocessing": {
    "normalize_l2": true,
    "pca_dim": null
  },
  "umap_params": {
    "n_neighbors": 15,
    "min_dist": 0.1,
    "spread": 1.0,
    "repulsion_strength": 1.0,
    "metric": "cosine",
    "random_state": 62
  },
  "clustering": {
    "n_clusters": 3,
    "method": "spherical_kmeans",
    "cluster_space": "hd"
  },
  "silhouette_cosine": 0.022202230989933014,
  "silhouette_euclidean": 0.01093310210853815,
  "embedding_shape": [
    498,
    96
  ]
}